{
  "$schema": "https://mintlify.com/docs.json",
  "theme": "maple",
  "name": "Thrads Documentation",
  "colors": {
    "primary": "#f8a497",
    "light": "#f8a497",
    "dark": "#e67262"
  },
  "favicon": "/favicon.svg",
  "navigation": {
    "tabs": [
      {
        "tab": "API Reference",
        "groups": [
          {
            "group": "API Documentation",
            "pages": [
              "api-reference/introduction"
            ]
          },
          {
            "group": "Endpoints",
            "pages": [
              "api-reference/endpoint/serve_ad",
              "api-reference/endpoint/sponsored_q",
              "api-reference/endpoint/delete"
            ]
          }
        ]
      },
      {
        "tab": "Guides",
        "groups": [
          {
            "group": "Guides",
            "pages": [
              "api-reference/guides/quickstart",
              "api-reference/guides/sponsored_messages_guide",
              "api-reference/guides/sponsored_questions_guide"
            ]
          }
        ]
      }
    ]
  },
  "logo": {
    "light": "/logo/light.svg",
    "dark": "/logo/dark.svg"
  },
  "navbar": {
    "links": [
      {
        "label": "Support",
        "href": "https://thrads.ai"
      }
    ],
    "primary": {
      "type": "button",
      "label": "Dashboard",
      "href": "https://thrads.ai"
    }
  },
  "footer": {
    "socials": {
      "x": "https://x.com",
      "github": "https://github.com",
      "linkedin": "https://www.linkedin.com/company/105776595"
    }
  }
}